{
  "title": "士燮-密探故事/03",
  "category": "密探故事",
  "characters": [
    "侍从",
    "儒士",
    "士燮",
    "我",
    "李君",
    "董奉"
  ],
  "content": [
    {
      "type": "dialogue",
      "speaker": "士燮",
      "text": "兄长的车马来迟了。",
      "emotion": ""
    },
    {
      "type": "dialogue",
      "speaker": "我",
      "text": "头像=广陵王-惊讶",
      "emotion": "……董奉？"
    },
    {
      "type": "dialogue",
      "speaker": "士燮",
      "text": "这是在做什么？快把长兄搀住。",
      "emotion": ""
    },
    {
      "type": "dialogue",
      "speaker": "士燮",
      "text": "诸位见笑。交州地处偏远，家法习俗，与此地有些许迥异。不过，虽然如此，我仍拿兄长当嫡亲的兄长对待。",
      "emotion": ""
    },
    {
      "type": "dialogue",
      "speaker": "士燮",
      "text": "——是不是？",
      "emotion": ""
    },
    {
      "type": "dialogue",
      "speaker": "李君",
      "text": "头像=黑人影",
      "emotion": "……是……太守对长公子十分礼遇……"
    },
    {
      "type": "dialogue",
      "speaker": "士燮",
      "text": "我在问我兄长。",
      "emotion": ""
    },
    {
      "type": "dialogue",
      "speaker": "士燮",
      "text": "兄长，殿下好像很担心你。说点什么，让广陵王安心吧？",
      "emotion": ""
    },
    {
      "type": "dialogue",
      "speaker": "董奉",
      "text": "我没事。",
      "emotion": ""
    },
    {
      "type": "dialogue",
      "speaker": "我",
      "text": "头像=广陵王-严肃",
      "emotion": "你在交州边境失踪，原来是与家人重逢了？如今既然平安归来……"
    },
    {
      "type": "dialogue",
      "speaker": "侍从",
      "text": "头像=侍从",
      "emotion": "……杏林君，先往内院歇息吧？"
    },
    {
      "type": "dialogue",
      "speaker": "我",
      "text": "头像=广陵王-点头",
      "emotion": "长途归来，定然劳累了。不必担心，夜宴上太守一行交由我们应酬便是。"
    },
    {
      "type": "dialogue",
      "speaker": "侍从",
      "text": "头像=侍从",
      "emotion": "……杏林君？殿下说了，走吧，没事的……"
    },
    {
      "type": "dialogue",
      "speaker": "董奉",
      "text": "……",
      "emotion": ""
    },
    {
      "type": "dialogue",
      "speaker": "士燮",
      "text": "这是在做什么？兄长离家出走多时，终于兄弟重逢。他是要与我们一同往许都，再同返交州的。",
      "emotion": ""
    },
    {
      "type": "dialogue",
      "speaker": "我",
      "text": "头像=广陵王-惊讶",
      "emotion": "只是请他往内院歇息，没说别的，更没有强行让兄弟生离。太守是怎么了？说话夹枪带棒的。"
    },
    {
      "type": "dialogue",
      "speaker": "我",
      "text": "头像=广陵王-微笑",
      "emotion": "许久不见，杏林君清减憔悴不少。途中若有什么委屈……"
    },
    {
      "type": "dialogue",
      "speaker": "儒士",
      "text": "头像=文官",
      "emotion": "是啊，看着精神不佳。而且交州竟有兄向弟行礼的礼数吗？不合尊卑啊。"
    },
    {
      "type": "dialogue",
      "speaker": "士燮",
      "text": "的确是陋习，所以我才求书心切，望改变民风。",
      "emotion": ""
    },
    {
      "type": "dialogue",
      "speaker": "士燮",
      "text": "交州苦热，各家先祖迁居之处生计艰难。世家为防家业流散、子嗣不和，便用了当地土人的习俗。",
      "emotion": ""
    },
    {
      "type": "dialogue",
      "speaker": "士燮",
      "text": "“子女凡不是正妻所出，皆与家奴无异”。",
      "emotion": ""
    },
    {
      "type": "dialogue",
      "speaker": "士燮",
      "text": "不过，我们之间如同嫡亲兄弟。兄长日常用度，一是在我的份例上再加一档的。",
      "emotion": ""
    },
    {
      "type": "dialogue",
      "speaker": "我",
      "text": "头像=广陵王-挑眉",
      "emotion": "如此兄友弟恭，当年又怎会闹到离家出走？"
    },
    {
      "type": "dialogue",
      "speaker": "士燮",
      "text": "是我不好。族务众多，频频劳动兄长。",
      "emotion": ""
    },
    {
      "type": "dialogue",
      "speaker": "我",
      "text": "头像=广陵王-微笑",
      "emotion": "什么族务？"
    },
    {
      "type": "dialogue",
      "speaker": "董奉",
      "text": "头像=董奉",
      "emotion": "……寻常族务罢了。"
    },
    {
      "type": "dialogue",
      "speaker": "董奉",
      "text": "头像=董奉",
      "emotion": "士氏兄弟之间并无罅隙。望殿下转告孟卓和元龙，不必担心，不必赶至广陵见我。"
    },
    {
      "type": "dialogue",
      "speaker": "士燮",
      "text": "这怎么行？此去千里，今生怕是都不得见了，分别前，不与友人们道个别吗？",
      "emotion": ""
    },
    {
      "type": "dialogue",
      "speaker": "我",
      "text": "头像=广陵王-微笑",
      "emotion": "……我和杏林君也相识多时。能否借一步说\n话？"
    },
    {
      "type": "dialogue",
      "speaker": "士燮",
      "text": "有什么见不得光的事，是要避开我这个弟弟的？",
      "emotion": ""
    },
    {
      "type": "dialogue",
      "speaker": "士燮",
      "text": "李君，兄长看起来忧思重重的。来的路上，我怎么嘱咐你的？务必无微不至服侍周到。若有一丝怠慢……",
      "emotion": ""
    },
    {
      "type": "dialogue",
      "speaker": "李君",
      "text": "头像=黑人影",
      "emotion": "我……是我做事不周……求长公子谅解……求太守宽恕……"
    },
    {
      "type": "dialogue",
      "speaker": "李君",
      "text": "头像=黑人影",
      "emotion": "求长公子……看在我作为李氏质子，从小在士氏被你看着长大的份上……求你留我一命……"
    },
    {
      "type": "dialogue",
      "speaker": "董奉",
      "text": "头像=董奉",
      "emotion": "他没做错。我也没有话需要私下说。"
    },
    {
      "type": "dialogue",
      "speaker": "士燮",
      "text": "殿下，听见了？",
      "emotion": ""
    },
    {
      "type": "dialogue",
      "speaker": "士燮",
      "text": "我们一行人将在广陵小住一月，等兄长的友人来，道完别，让他无牵无挂回去。",
      "emotion": ""
    },
    {
      "type": "dialogue",
      "speaker": "士燮",
      "text": "看看，兄长这次不告而别，把李君吓成什么样了。虽是四大家族中的李氏送来的质子，但也情同手足啊。",
      "emotion": ""
    },
    {
      "type": "dialogue",
      "speaker": "士燮",
      "text": "兄长走后，好几个异姓兄弟对你思念成疾，早早去了谁能忍心李君也命不长久？",
      "emotion": ""
    },
    {
      "type": "dialogue",
      "speaker": "李君",
      "text": "头像=黑人影",
      "emotion": "……长公子……壹哥……士壹……"
    },
    {
      "type": "dialogue",
      "speaker": "我",
      "text": "头像=广陵王-愤怒",
      "emotion": "够了。千里迢迢来广陵，当面来这一出，太守想做什么？"
    },
    {
      "type": "dialogue",
      "speaker": "士燮",
      "text": "不做什么呀。家事而已，殿下是怎么了？说话夹枪带棒的。",
      "emotion": ""
    },
    {
      "type": "dialogue",
      "speaker": "我",
      "text": "头像=广陵王-严肃",
      "emotion": "既然太守不想我们私下说话，那就不顾及什么脸面了。他拿什么要挟你，董奉？"
    },
    {
      "type": "dialogue",
      "speaker": "董奉",
      "text": "……",
      "emotion": ""
    },
    {
      "type": "dialogue",
      "speaker": "我",
      "text": "头像=广陵王-微笑",
      "emotion": "直接说。是眼前李氏子的命吗？还是在交州有其他牵挂？"
    },
    {
      "type": "dialogue",
      "speaker": "董奉",
      "text": "……",
      "emotion": ""
    },
    {
      "type": "dialogue",
      "speaker": "我",
      "text": "头像=广陵王-微笑",
      "emotion": "去取袁氏的书信来。"
    },
    {
      "type": "dialogue",
      "speaker": "侍从",
      "text": "头像=侍从",
      "emotion": "……哪一卷？"
    },
    {
      "type": "dialogue",
      "speaker": "我",
      "text": "头像=广陵王-挑眉",
      "emotion": "随便。"
    },
    {
      "type": "dialogue",
      "speaker": "我",
      "text": "头像=广陵王-严肃",
      "emotion": "太守，非是王府想为难贵客。实在是董奉身上有旧案未结。"
    },
    {
      "type": "dialogue",
      "speaker": "我",
      "text": "头像=广陵王-严肃",
      "emotion": "袁氏四世三公，长公子此前因伤目盲。他前去出诊，却让对方病情加重……"
    },
    {
      "type": "dialogue",
      "speaker": "我",
      "text": "头像=广陵王-严肃",
      "emotion": "这些都是袁氏问责的书信，严令这边追捕董奉，查清他是否受人致使，借行医之名行刺。"
    },
    {
      "type": "dialogue",
      "speaker": "我",
      "text": "头像=广陵王-严肃",
      "emotion": "董奉，你也太不谨慎了。长公子何等金尊玉贵的人物，你怎敢轻慢？如今袁氏问责，本地不敢包庇。"
    },
    {
      "type": "dialogue",
      "speaker": "我",
      "text": "头像=广陵王-严肃",
      "emotion": "来人，将他押下，关入牢中，等候袁氏使者。"
    },
    {
      "type": "narration",
      "text": "\"\""
    }
  ],
  "source_url": "https://wiki.biligame.com/yuan/%E5%A3%AB%E7%87%AE-%E5%AF%86%E6%8E%A2%E6%95%85%E4%BA%8B/03",
  "crawled_at": "2026-04-12T22:24:12.829836",
  "raw_wikitext": "{{密探故事录入|头|士燮|03}}{{旁白|【夜宴】}}\n{{对话|士燮|兄长的车马来迟了。}}\n{{旁白|步辇直接被抬入席上，左右侍卫将他搀扶起身，缓缓上前。}}\n{{对话|我|……董奉？|头像=广陵王-惊讶}}\n{{旁白|没有回答。}}\n{{旁白|就像李君一样，他在士燮面前停下，欲行大礼。因为被卸去义肢，少了一条腿，行动格外艰难。}}\n{{对话|士燮|这是在做什么？快把长兄搀住。}}\n{{对话|士燮|诸位见笑。交州地处偏远，家法习俗，与此地有些许迥异。不过，虽然如此，我仍拿兄长当嫡亲的兄长对待。}}\n{{对话|士燮|——是不是？}}\n{{对话|李君|……是……太守对长公子十分礼遇……|头像=黑人影}}\n{{对话|士燮|我在问我兄长。}}\n{{旁白|李君抖若筛糠跪下；士燮看向董奉，微微含笑。}}\n{{对话|士燮|兄长，殿下好像很担心你。说点什么，让广陵王安心吧？}}\n{{对话|董奉|我没事。}}\n{{对话|我|你在交州边境失踪，原来是与家人重逢了？如今既然平安归来……|头像=广陵王-严肃}}\n{{旁白|侍从会意，立刻带着两人走到他身侧，将他和士氏的人隔开。}}\n{{对话|侍从|……杏林君，先往内院歇息吧？|头像=侍从}}\n{{对话|我|长途归来，定然劳累了。不必担心，夜宴上太守一行交由我们应酬便是。|头像=广陵王-点头}}\n{{对话|侍从|……杏林君？殿下说了，走吧，没事的……|头像=侍从}}\n{{对话|董奉|……}}\n{{对话|士燮|这是在做什么？兄长离家出走多时，终于兄弟重逢。他是要与我们一同往许都，再同返交州的。}}\n{{对话|我|只是请他往内院歇息，没说别的，更没有强行让兄弟生离。太守是怎么了？说话夹枪带棒的。|头像=广陵王-惊讶}}\n{{对话|我|许久不见，杏林君清减憔悴不少。途中若有什么委屈……|头像=广陵王-微笑}}\n{{对话|儒士|是啊，看着精神不佳。而且交州竟有兄向弟行礼的礼数吗？不合尊卑啊。|头像=文官}}\n{{对话|士燮|的确是陋习，所以我才求书心切，望改变民风。}}\n{{对话|士燮|交州苦热，各家先祖迁居之处生计艰难。世家为防家业流散、子嗣不和，便用了当地土人的习俗。}}\n{{对话|士燮|“子女凡不是正妻所出，皆与家奴无异”。}}\n{{对话|士燮|不过，我们之间如同嫡亲兄弟。兄长日常用度，一是在我的份例上再加一档的。}}\n{{对话|我|如此兄友弟恭，当年又怎会闹到离家出走？|头像=广陵王-挑眉}}\n{{对话|士燮|是我不好。族务众多，频频劳动兄长。}}\n{{对话|我|什么族务？|头像=广陵王-微笑}}\n{{对话|董奉|……寻常族务罢了。|头像=董奉}}\n{{对话|董奉|士氏兄弟之间并无罅隙。望殿下转告孟卓和元龙，不必担心，不必赶至广陵见我。|头像=董奉}}\n{{对话|士燮|这怎么行？此去千里，今生怕是都不得见了，分别前，不与友人们道个别吗？}}\n\"{{对话|我|……我和杏林君也相识多时。能否借一步说\n话？|头像=广陵王-微笑}}\"\n{{旁白|董奉抬头看向我，缓缓摇了摇头。}}\n{{对话|士燮|有什么见不得光的事，是要避开我这个弟弟的？}}\n{{对话|士燮|李君，兄长看起来忧思重重的。来的路上，我怎么嘱咐你的？务必无微不至服侍周到。若有一丝怠慢……}}\n{{对话|李君|我……是我做事不周……求长公子谅解……求太守宽恕……|头像=黑人影}}\n{{对话|李君|求长公子……看在我作为李氏质子，从小在士氏被你看着长大的份上……求你留我一命……|头像=黑人影}}\n{{对话|董奉|他没做错。我也没有话需要私下说。|头像=董奉}}\n{{对话|士燮|殿下，听见了？}}\n{{旁白|他的笑眼看了过来，那笑意柔美，但含着一缕森然的挑衅。}}\n{{对话|士燮|我们一行人将在广陵小住一月，等兄长的友人来，道完别，让他无牵无挂回去。}}\n{{对话|士燮|看看，兄长这次不告而别，把李君吓成什么样了。虽是四大家族中的李氏送来的质子，但也情同手足啊。}}\n{{对话|士燮|兄长走后，好几个异姓兄弟对你思念成疾，早早去了谁能忍心李君也命不长久？}}\n{{对话|李君|……长公子……壹哥……士壹……|头像=黑人影}}\n{{旁白|他膝行到董奉座前，颤抖着抓住董奉的衣角，匍匐低哭。那人目光死寂，看不出任何喜悲。}}\n{{对话|我|够了。千里迢迢来广陵，当面来这一出，太守想做什么？|头像=广陵王-愤怒}}\n{{对话|士燮|不做什么呀。家事而已，殿下是怎么了？说话夹枪带棒的。}}\n{{对话|我|既然太守不想我们私下说话，那就不顾及什么脸面了。他拿什么要挟你，董奉？|头像=广陵王-严肃}}\n{{对话|董奉|……}}\n{{对话|我|直接说。是眼前李氏子的命吗？还是在交州有其他牵挂？|头像=广陵王-微笑}}\n{{对话|董奉|……}}\n{{旁白|心理|不行，必须强行把他们隔开。这个人在场，董奉一句话都不能多说。}}\n{{对话|我|去取袁氏的书信来。|头像=广陵王-微笑}}\n{{对话|侍从|……哪一卷？|头像=侍从}}\n{{对话|我|随便。|头像=广陵王-挑眉}}\n{{对话|我|太守，非是王府想为难贵客。实在是董奉身上有旧案未结。|头像=广陵王-严肃}}\n{{对话|我|袁氏四世三公，长公子此前因伤目盲。他前去出诊，却让对方病情加重……|头像=广陵王-严肃}}\n{{旁白|侍从匆忙带了一匣不知何年何月的书信卷轴回来，我取过匣子，重重放在案上。}}\n{{对话|我|这些都是袁氏问责的书信，严令这边追捕董奉，查清他是否受人致使，借行医之名行刺。|头像=广陵王-严肃}}\n{{对话|我|董奉，你也太不谨慎了。长公子何等金尊玉贵的人物，你怎敢轻慢？如今袁氏问责，本地不敢包庇。|头像=广陵王-严肃}}\n{{对话|我|来人，将他押下，关入牢中，等候袁氏使者。|头像=广陵王-严肃}}\n{{密探故事录入|尾|士燮|03}}"
}